pg_upsert/__init__.py
pg_upsert/__main__.py
pg_upsert/__version__.py
pg_upsert/cli.py
pg_upsert/postgres.py
pg_upsert/ui.py
pg_upsert/upsert.py
pg_upsert/utils.py
pg_upsert-1.5.3.dist-info/LICENSE
pg_upsert-1.5.3.dist-info/METADATA
pg_upsert-1.5.3.dist-info/WHEEL
pg_upsert-1.5.3.dist-info/entry_points.txt
pg_upsert-1.5.3.dist-info/top_level.txt
pg_upsert-1.5.3.dist-info/RECORD
