Metadata-Version: 2.2
Name: pg_upsert
Version: 1.5.3
Summary: A Python library for upserting data into postgres.
Author-email: Caleb Grant <grantcaleb22@gmail.com>
License:                     GNU GENERAL PUBLIC LICENSE
Project-URL: Homepage, https://pg-upsert.readthedocs.io
Project-URL: Repository, https://github.com/geocoug/pg-upsert
Project-URL: Issues, https://github.com/geocoug/pg-upsert/issues
Keywords: postgresql,postgres,dbms,etl,upsert,database
Classifier: Programming Language :: Python :: 3
Classifier: Programming Language :: Python :: 3.10
Classifier: Programming Language :: Python :: 3.11
Classifier: Programming Language :: Python :: 3.12
Classifier: Programming Language :: Python :: 3.13
Classifier: Operating System :: OS Independent
Classifier: Intended Audience :: Developers
Classifier: Topic :: Database
Classifier: Topic :: Software Development :: Libraries :: Python Modules
Classifier: License :: OSI Approved :: GNU Lesser General Public License v3 (LGPLv3)
Requires-Python: <3.14,>=3.10
License-File: LICENSE
Requires-Dist: psycopg2-binary<3,>=2.9
Requires-Dist: tabulate<0.10,>=0.9
Requires-Dist: pyyaml<7,>=6.0.1
Requires-Dist: typer<0.16,>=0.15
Provides-Extra: dev
Requires-Dist: build; extra == "dev"
Requires-Dist: bump-my-version; extra == "dev"
Requires-Dist: markdown-include; extra == "dev"
Requires-Dist: mkdocs; extra == "dev"
Requires-Dist: mkdocstrings; extra == "dev"
Requires-Dist: mkdocstrings-python; extra == "dev"
Requires-Dist: mkdocs-material; extra == "dev"
Requires-Dist: pre-commit; extra == "dev"
Requires-Dist: pytest; extra == "dev"
Requires-Dist: pytest-cov; extra == "dev"
Requires-Dist: python-dotenv; extra == "dev"
Requires-Dist: ruff; extra == "dev"
Requires-Dist: tox-uv; extra == "dev"
Requires-Dist: twine; extra == "dev"
